Workbook

Sheet README
A1: BU Transfer Credit Evaluation: Synthetic Data Pack
A2: Status | B2: SYNTHETIC. Generated for FDE AI Hackathon 5.0, Problem 1. Students, transcripts, decisions, evaluators, syllabi and the two fictional schools are invented. Not official BU equivalencies.
A3: Builds on | B3: BU_Transfer_Program_Course_Match.xlsx (supplied). Course codes, titles and credits for BU, Northeastern and NYU come from it; descriptions and learning outcomes were written for the hackathon.
A4: Fictional schools | B4: Harborview Community College (fictional): semester system, used for the community-college demo. Pacific Crest University (fictional): quarter system, used to test the 2/3 credit conversion.
A6: Sheets
A7: Institutions | B7: The five sending/receiving institutions and their credit systems.
A8: Course Catalog | B8: All courses with description and learning outcomes: the text the AI matcher compares.
A9: Transfer Rules | B9: Machine-readable rules (grade, quarter conversion, Hub, deadline, Group C, Econ cap, Biology residency) with their source.
A10: Past Decisions | B10: Evaluator decisions with rationale (Active and Superseded). Use as few-shot examples and to measure matcher accuracy.
A11: Equivalency DB | B11: Active, reusable decisions: the lookup table checked first (steps 3-4 of BU's process).
A12: Students / Transcript Lines | B12: 5 synthetic students and 35 transcript lines. SYN-1001 is the suggested demo scenario.
A13: Syllabi | B13: Index of 4 syllabus PDFs for courses with no existing equivalency.
A14: Answer Key | B14: Expected outcome per transcript line. Hide it from the agent; use it to score the agent.
A15: Summary | B15: Formula checks: counts by outcome and secure/pending units per student.
A17: Files | B17: transcripts/*.pdf: one synthetic transcript per student per institution (upload input). syllabi/*.pdf: the 4 syllabi.
A19: Assumptions (confirm with sponsor)
A20: A1 | B20: Quarter conversion truncates to 2 decimals (4 qtr = 2.66, 5 qtr = 3.33), matching BU's own example.
A21: A2 | B21: Units awarded = sending-school credits (after conversion), even when the BU course is 4 credits (e.g. NU 5-credit lab courses award 5).
A22: A3 | B22: CS Group C courses taken elsewhere earn CS elective credit but never satisfy the Group C requirement.
A23: A4 | B23: Pass/Fail grades are held for evaluator decision because a C or higher cannot be confirmed.
A24: A5 | B24: Developmental (pre-college) courses earn no credit.
A25: A6 | B25: The one-year deadline is measured from BU start date to the date the transcript is received.
A26: A7 | B26: Courses missing from the catalogue (ENGW 1111, EXPOS-UA 1) are deliberate: the agent should request a syllabus, not guess.

Sheet Institutions
A1: Institution | B1: Type | C1: Credit system | D1: Conversion to BU semester credits | E1: Data origin
A2: Boston University | B2: Receiving university | C2: Semester | D2: — | E2: Supplied workbook
A3: Northeastern University | B3: Peer university | C3: Semester | D3: 1:1 | E3: Supplied workbook + synthetic descriptions
A4: New York University | B4: Peer university | C4: Semester | D4: 1:1 | E4: Supplied workbook + synthetic descriptions
A5: Harborview Community College (fictional) | B5: Community college | C5: Semester | D5: 1:1 | E5: Fully synthetic
A6: Pacific Crest University (fictional) | B6: University | C6: Quarter | D6: × 2/3, truncated to 2 dp | E6: Fully synthetic

Sheet Course Catalog
A1: Institution | B1: Course code | C1: Course title | D1: Program | E1: Credits | F1: Credit system | G1: Description | H1: Learning outcomes | I1: Data origin
A2: Boston University | B2: CAS CS 111 | C2: Introduction to Computer Science 1 | D2: Computer Science | E2: 4 | F2: Semester | G2: Introduction to programming and computational problem solving in a high-level language (Python). Covers variables, control flow, functions, recursion, lists and dictionaries, file input/output, an introduction to classes and objects, and testing and debugging practice. | H2: Write, test and debug programs of moderate size Decompose problems into functions, including recursive solutions Use lists, dictionaries and simple classes | I2: Code/title/credits from supplied workbook; description & outcomes synthetic
A3: Boston University | B3: CAS CS 112 | C3: Introduction to Computer Science 2 | D3: Computer Science | E3: 4 | F3: Semester | G3: Second programming course focused on data structures and their analysis, taught in an object-oriented language (Java). Covers linked lists, stacks, queues, trees, binary search trees, heaps, hash tables and an introduction to graphs, with Big-O analysis of each operation. | H3: Implement and use core data structures Analyse time and space complexity using Big-O notation Select an appropriate data structure for a given problem | I3: Code/title/credits from supplied workbook; description & outcomes synthetic
A4: Boston University | B4: CAS CS 131 | C4: Combinatoric Structures | D4: Computer Science | E4: 4 | F4: Semester | G4: Mathematical foundations of computer science: propositional and predicate logic, proof techniques, induction, sets, functions and relations, counting and combinatorics, recurrence relations, graphs and trees, and an introduction to discrete probability. | H4: Construct direct, contradiction and induction proofs Solve counting problems and recurrences Reason about graphs and basic discrete probability | I4: Code/title/credits from supplied workbook; description & outcomes synthetic
A5: Boston University | B5: CAS CS 210 | C5: Computer Systems | D5: Computer Science | E5: 4 | F5: Semester | G5: How programs execute on real machines: data representation, C programming, assembly language, memory hierarchy and caches, linking, processes and an introduction to concurrency. | H5: Write and debug C programs Explain how high-level code maps to machine instructions Reason about memory and cache performance | I5: Code/title/credits from supplied workbook; description & outcomes synthetic
A6: Boston University | B6: CAS CS 330 | C6: Introduction to the Analysis of Algorithms | D6: Computer Science | E6: 4 | F6: Semester | G6: Design and analysis of algorithms: divide and conquer, greedy methods, dynamic programming, graph algorithms (search, shortest paths, minimum spanning trees), network flow and NP-completeness, with proofs of correctness and running time. | H6: Design algorithms using standard paradigms Prove correctness and running time Recognise intractable problems | I6: Code/title/credits from supplied workbook; description & outcomes synthetic
A7: Boston University | B7: CAS CS 132 | C7: Geometric Algorithms | D7: Computer Science | E7: 4 | F7: Semester | G7: Linear algebra from a computational perspective: vectors, matrices, linear transformations, eigenvalues and least squares, applied to graphics, data analysis and machine learning, with programming assignments in Python. | H7: Perform core matrix computations Apply linear algebra to computational problems Implement linear-algebra algorithms in code | I7: Code/title/credits from supplied workbook; description & outcomes synthetic
A8: Boston University | B8: CAS CS 235 | C8: Algebraic Algorithms | D8: Computer Science | E8: 4 | F8: Semester | G8: Algorithms for algebraic structures: modular arithmetic, groups, rings and fields, polynomials, and applications to cryptography and error-correcting codes. | H8: Compute in modular and polynomial arithmetic Explain algebraic structures used in cryptography Implement basic cryptographic algorithms | I8: Code/title/credits from supplied workbook; description & outcomes synthetic
A9: Boston University | B9: CAS CS 237 | C9: Probability in Computing | D9: Computer Science | E9: 4 | F9: Semester | G9: Probability for computing: sample spaces, conditional probability, random variables, expectation and variance, common distributions, tail bounds and applications to randomised algorithms and simulation. | H9: Compute probabilities and expectations Apply common distributions and tail bounds Analyse simple randomised algorithms | I9: Code/title/credits from supplied workbook; description & outcomes synthetic
A10: Boston University | B10: CAS CS 320 | C10: Concepts of Programming Languages | D10: Computer Science | E10: 4 | F10: Semester | G10: Concepts of programming languages: syntax and semantics, interpreters, scope, type systems, functional programming and language design trade-offs. | H10: Build a small interpreter Explain type systems and scoping rules Compare language design choices | I10: Code/title/credits from supplied workbook; description & outcomes synthetic
A11: Boston University | B11: CAS CS 332 | C11: Elements of the Theory of Computation | D11: Computer Science | E11: 4 | F11: Semester | G11: Theory of computation: finite automata, regular languages, context-free grammars, Turing machines, decidability and an introduction to the complexity classes P and NP. | H11: Construct automata and grammars Prove languages non-regular or undecidable Explain P versus NP | I11: Code/title/credits from supplied workbook; description & outcomes synthetic
A12: Boston University | B12: CAS CS 350 | C12: Fundamentals of Computing Systems | D12: Computer Science | E12: 4 | F12: Semester | G12: Fundamentals of computing systems: performance modelling, queuing, scheduling, concurrency and synchronisation, and operating-system resource management. | H12: Model system performance Write correct concurrent code Explain OS resource management | I12: Code/title/credits from supplied workbook; description & outcomes synthetic
A13: Boston University | B13: CAS EC 101 | C13: Introductory Microeconomic Analysis | D13: Economics | E13: 4 | F13: Semester | G13: Principles of microeconomics: supply and demand, consumer and producer behaviour, market structures, market failure and the role of government. | H13: Use supply and demand to analyse markets Compare market structures Evaluate policy responses to market failure | I13: Code/title/credits from supplied workbook; description & outcomes synthetic
... A155: Pacific Crest University (fictional) | B155: CHEM 237 | C155: Organic Chemistry I | D155: Chemistry | E155: 4 | F155: Quarter | G155: Organic chemistry I (quarter): bonding, structure, stereochemistry and an introduction to substitution reactions. Elimination reactions and alkenes are covered in the next quarter. Laboratory is a separate course. | H155: Draw organic structures Explain stereochemistry Predict substitution mechanisms | I155: Fully synthetic

Sheet Transfer Rules
A1: Rule ID | B1: Rule | C1: Parameter | D1: Applies to | E1: Agent action | F1: Source
A2: R1 | B2: Minimum grade | C2: C (C- or lower = no credit) | D2: All courses | E2: Set units to 0 and explain | F2: Problem statement (many BU schools)
A3: R2 | B3: Quarter conversion | C3: × 2/3, truncate to 2 dp | D3: Quarter-system schools | E3: Convert units before posting | F3: Problem statement; truncation = assumption A1
A4: R3 | B4: No Hub units | C4: 0 Hub units | D4: All transfer courses | E4: Never award Hub units | F4: Problem statement
A5: R4 | B5: Deadline | C5: 365 days from BU start | D5: All transcripts | E5: Flag; posting needs an exception | F5: Problem statement; measurement = assumption A6
A6: R5 | B6: External grades excluded from GPA | C6: Grade posted as T | D6: All courses | E6: Post grade T | F6: Problem statement
A7: R6 | B7: CS Group C BU-only | C7: CAS CS 320, 332, 350 | D7: BA Computer Science | E7: Elective credit only; requirement not satisfied | F7: Supplied workbook (Programs); assumption A3
A8: R7 | B8: Economics 200+ cap | C8: Max 4 courses at 200+ level after matriculation | D8: BA Economics | E8: Hold the 5th and later; evaluator chooses | F8: Supplied workbook (Programs)
A9: R8 | B9: Biology residency | C9: ≥ 5 BI courses beyond BI 107/108 at BU | D9: BA Biology | E9: Warn when transfers would exceed the limit | F9: Supplied workbook (Programs)
A10: R9 | B10: Pass/Fail | C10: Cannot confirm ≥ C | D10: All courses | E10: Hold for evaluator | F10: Assumption A4
A11: R10 | B11: Developmental courses | C11: No credit | D11: Pre-college courses | E11: Set units to 0 | F11: Assumption A5
A12: R11 | B12: Final decision | C12: Department evaluator | D12: All new matches | E12: Recommend only; never post a new equivalency automatically | F12: Problem statement (ground rule)

Sheet Past Decisions
A1: Decision ID | B1: Decision date | C1: Source institution | D1: Source course | E1: Source title | F1: Source credits | G1: Credit system | H1: Outcome | I1: BU course awarded | J1: BU title | K1: BU units awarded | L1: Requirement satisfied | M1: Syllabus reviewed | N1: Department | O1: Evaluator ID | P1: Status | Q1: Reusable | R1: Rationale
A2: D-001 | B2: 44213 | C2: New York University | D2: PSYCH-UA 32 | E2: Social Psychology | F2: 4 | G2: Semester | H2: BU equivalent | I2: CAS PS 261 | J2: Social Psychology | K2: 4 | L2: Yes | M2: Yes | N2: CAS Psychological & Brain Sciences | O2: EVAL-PSY-03 | P2: Active | Q2: Yes | R2: Content and level align with CAS PS 261 (Social Psychology).
A3: D-002 | B3: 44219 | C3: Pacific Crest University (fictional) | D3: PSYCH 101 | E3: Psychology as a Science | F3: 5 | G3: Quarter | H3: BU equivalent | I3: CAS PS 101 | J3: General Psychology | K3: 3.33 | L3: Yes | M3: No | N3: CAS Psychological & Brain Sciences | O3: EVAL-PSY-02 | P3: Active | Q3: Yes | R3: Intro psychology. Meets PS 101.
A4: D-003 | B4: 44258 | C4: New York University | D4: ECON-UA 10 | E4: Intermediate Microeconomics | F4: 4 | G4: Semester | H4: BU equivalent | I4: CAS EC 201 | J4: Intermediate Microeconomic Analysis | K4: 4 | L4: Yes | M4: Yes | N4: CAS Economics | O4: EVAL-ECO-02 | P4: Active | Q4: Yes | R4: Content and level align with CAS EC 201 (Intermediate Microeconomic Analysis).
A5: D-004 | B5: 44271 | C5: Pacific Crest University (fictional) | D5: MATH 125 | E5: Calculus II | F5: 5 | G5: Quarter | H5: BU equivalent | I5: CAS MA 124 | J5: Calculus II | K5: 3.33 | L5: Yes | M5: Yes | N5: CAS Mathematics & Statistics | O5: EVAL-MAT-01 | P5: Active | Q5: Yes | R5: Quarter calculus II (integration). Accepted for MA 124.
A6: D-005 | B6: 44313 | C6: Northeastern University | D6: CS 2000 | E6: Introduction to Program Design and Implementation | F6: 5 | G6: Semester | H6: BU equivalent | I6: CAS CS 111 | J6: Introduction to Computer Science 1 | K6: 5 | L6: Yes | M6: Yes | N6: CAS Computer Science | O6: EVAL-COM-01 | P6: Active | Q6: Yes | R6: Content and level align with CAS CS 111 (Introduction to Computer Science 1).
A7: D-006 | B7: 44319 | C7: Northeastern University | D7: CS 3800 | E7: Theory of Computation | F7: 4 | G7: Semester | H7: Elective credit | I7: CAS CS elective | J7: — | K7: 4 | L7: No | M7: No | N7: CAS Computer Science | O7: EVAL-COM-01 | P7: Active | Q7: Yes | R7: Comparable to CAS CS 332, but CS Group C courses must be taken at BU. Elective credit only.
A8: D-007 | B8: 44341 | C8: Northeastern University | D8: CS 3000 | E8: Algorithms and Data | F8: 4 | G8: Semester | H8: BU equivalent | I8: CAS CS 330 | J8: Introduction to the Analysis of Algorithms | K8: 4 | L8: Yes | M8: Yes | N8: CAS Computer Science | O8: EVAL-COM-02 | P8: Active | Q8: Yes | R8: Content and level align with CAS CS 330 (Introduction to the Analysis of Algorithms).
A9: D-008 | B9: 44350 | C9: Harborview Community College (fictional) | D9: CSC 110 | E9: Introduction to Programming (Python) | F9: 4 | G9: Semester | H9: Elective credit | I9: CAS CS elective | J9: — | K9: 4 | L9: No | M9: Yes | N9: CAS Computer Science | O9: EVAL-COM-02 | P9: Superseded | Q9: No | R9: 2021 syllabus taught spreadsheet macros, not general programming. Superseded after course redesign.
A10: D-009 | B10: 44432 | C10: Harborview Community College (fictional) | D10: PSY 210 | E10: Lifespan Development | F10: 3 | G10: Semester | H10: Elective credit | I10: CAS PS elective | J10: — | K10: 3 | L10: No | M10: Yes | N10: CAS Psychological & Brain Sciences | O10: EVAL-PSY-03 | P10: Active | Q10: Yes | R10: Lifespan survey; child/adolescent development is about one third of the course, below PS 241 depth.
A11: D-010 | B11: 44440 | C11: Northeastern University | D11: MATH 1341 | E11: Calculus 1 for Science and Engineering | F11: 4 | G11: Semester | H11: BU equivalent | I11: CAS MA 123 | J11: Calculus I | K11: 4 | L11: Yes | M11: Yes | N11: CAS Mathematics & Statistics | O11: EVAL-MAT-02 | P11: Active | Q11: Yes | R11: Content and level align with CAS MA 123 (Calculus I).
A12: D-011 | B12: 44448 | C12: New York University | D12: BIOL-UA 11 | E12: Principles of Biology I | F12: 4 | G12: Semester | H12: BU equivalent | I12: CAS BI 107 | J12: Biology 1 | K12: 4 | L12: Yes | M12: No | N12: CAS Biology | O12: EVAL-BIO-01 | P12: Active | Q12: Yes | R12: Content and level align with CAS BI 107 (Biology 1).
A13: D-012 | B13: 44452 | C13: Harborview Community College (fictional) | D13: CSC 110 | E13: Introduction to Programming (Python) | F13: 4 | G13: Semester | H13: BU equivalent | I13: CAS CS 111 | J13: Introduction to Computer Science 1 | K13: 4 | L13: Yes | M13: Yes | N13: CAS Computer Science | O13: EVAL-COM-03 | P13: Active | Q13: Yes | R13: Syllabus confirms Python, recursion, dictionaries and intro to classes. Meets CS 111.
... A112: D-111 | B112: 46255 | C112: Northeastern University | D112: MATH 2341 | E112: Differential Equations and Linear Algebra for Engineering | F112: 4 | G112: Semester | H112: Elective credit | I112: CAS MA elective | J112: — | K112: 4 | L112: No | M112: Yes | N112: CAS Mathematics & Statistics | O112: EVAL-MAT-01 | P112: Active | Q112: Yes | R112: Half-depth ODE coverage combined with linear algebra; does not meet MA 226.

Sheet Equivalency DB
A1: Source institution | B1: Source course | C1: Source title | D1: Outcome | E1: BU equivalent | F1: BU units (converted) | G1: Requirement satisfied | H1: Effective date | I1: Review by | J1: Decision ID
A2: Harborview Community College (fictional) | B2: BIO 121 | C2: General Biology I | D2: BU equivalent | E2: CAS BI 107 | F2: 4 | G2: Yes | H2: 44614 | I2: 46440 | J2: D-026
A3: Harborview Community College (fictional) | B3: BIO 122 | C3: General Biology II | D3: BU equivalent | E3: CAS BI 108 | F3: 4 | G3: Yes | H3: 45860 | I3: 47686 | J3: D-087
A4: Harborview Community College (fictional) | B4: CHM 121 | C4: General Chemistry I | D4: BU equivalent | E4: CAS CH 101 | F4: 4 | G4: Yes | H4: 45600 | I4: 47426 | J4: D-073
A5: Harborview Community College (fictional) | B5: CHM 122 | C5: General Chemistry II | D5: BU equivalent | E5: CAS CH 102 | F5: 4 | G5: Yes | H5: 45229 | I5: 47055 | J5: D-055
A6: Harborview Community College (fictional) | B6: COM 105 | C6: Public Speaking | D6: Elective credit | E6: COM general elective | F6: 3 | G6: No | H6: 45939 | I6: 47765 | J6: D-089
A7: Harborview Community College (fictional) | B7: CSC 110 | C7: Introduction to Programming (Python) | D7: BU equivalent | E7: CAS CS 111 | F7: 4 | G7: Yes | H7: 44452 | I7: 46278 | J7: D-012
A8: Harborview Community College (fictional) | B8: CSC 120 | C8: Computer Applications | D8: No credit | E8: — | F8: 0 | G8: No | H8: 44487 | I8: 46313 | J8: D-016
A9: Harborview Community College (fictional) | B9: ECO 201 | C9: Principles of Macroeconomics | D9: BU equivalent | E9: CAS EC 102 | F9: 3 | G9: Yes | H9: 45976 | I9: 47802 | J9: D-093
A10: Harborview Community College (fictional) | B10: ECO 202 | C10: Principles of Microeconomics | D10: BU equivalent | E10: CAS EC 101 | F10: 3 | G10: Yes | H10: 45945 | I10: 47771 | J10: D-091
A11: Harborview Community College (fictional) | B11: ENG 101 | C11: English Composition I | D11: Elective credit | E11: CAS general elective | F11: 3 | G11: No | H11: 44990 | I11: 46816 | J11: D-039
A12: Harborview Community College (fictional) | B12: ENG 102 | C12: English Composition II | D12: Elective credit | E12: CAS general elective | F12: 3 | G12: No | H12: 44608 | I12: 46434 | J12: D-024
A13: Harborview Community College (fictional) | B13: HIS 111 | C13: U.S. History I | D13: Elective credit | E13: CAS HI elective | F13: 3 | G13: No | H13: 44990 | I13: 46816 | J13: D-040
... A109: Pacific Crest University (fictional) | B109: STAT 311 | C109: Elements of Statistics | D109: Elective credit | E109: CAS MA elective | F109: 3.33 | G109: No | H109: 46182 | I109: 48008 | J109: D-107

Sheet Students
A1: Student ID | B1: Name (fictional) | C1: Intended BU program | D1: BU start date | E1: Deadline (start + 365 days) | F1: Prior 200+ ECON transfers after matriculation | G1: Scenario
A2: SYN-1001 | B2: Jordan Alvarez | C2: BA in Computer Science | D2: 46267 | E2: =D2+365 -> 46632 | F2: 0 | G2: Demo scenario: 6 courses (3 existing equivalencies, 2 'maybe', 1 quarter-system).
A3: SYN-1002 | B3: Priya Raman | C3: BA in Computer Science | D3: 46267 | E3: =D3+365 -> 46632 | F3: 0 | G3: Northeastern transfer: Group C rule, grade below C, 5-credit lab courses, course with no catalogue data.
A4: SYN-1003 | B4: Daniel Kim | C4: BA in Psychology | D4: 46267 | E4: =D4+365 -> 46632 | F4: 0 | G4: NYU transfer: partial matches, a Pass/Fail grade, a 'maybe' with no decision, and an unlisted course.
A5: SYN-1004 | B5: Aisha Thompson | C5: BA in Biology | D5: 46042 | E5: =D5+365 -> 46407 | F5: 0 | G5: Community college + quarter school: developmental course, quarter conversion, and a transcript received after the one-year deadline.
A6: SYN-1005 | B6: Marcus Lee | C6: BA in Economics | D6: 45902 | E6: =D6+365 -> 46267 | F6: 2 | G6: Current BU student taking summer courses after matriculation: tests the 4-course cap on 200+ level Economics transfers.

Sheet Transcript Lines
A1: Line ID | B1: Student ID | C1: Institution | D1: Credit system | E1: Term | F1: Course code | G1: Course title | H1: Credits | I1: Grade | J1: Taken after BU matriculation | K1: Transcript received
A2: TL-001 | B2: SYN-1001 | C2: Harborview Community College (fictional) | D2: Semester | E2: Fall 2024 | F2: CSC 110 | G2: Introduction to Programming (Python) | H2: 4 | I2: A | J2: No | K2: 46193
A3: TL-002 | B3: SYN-1001 | C3: Harborview Community College (fictional) | D3: Semester | E3: Fall 2024 | F3: MAT 151 | G3: Calculus I | H3: 4 | I3: B+ | J3: No | K3: 46193
A4: TL-003 | B4: SYN-1001 | C4: Harborview Community College (fictional) | D4: Semester | E4: Fall 2024 | F4: ENG 101 | G4: English Composition I | H4: 3 | I4: A- | J4: No | K4: 46193
A5: TL-004 | B5: SYN-1001 | C5: Harborview Community College (fictional) | D5: Semester | E5: Spring 2025 | F5: CSC 215 | G5: Data Structures in Java | H5: 4 | I5: B | J5: No | K5: 46193
A6: TL-005 | B6: SYN-1001 | C6: Harborview Community College (fictional) | D6: Semester | E6: Spring 2025 | F6: MAT 210 | G6: Discrete Mathematics | H6: 3 | I6: B | J6: No | K6: 46193
A7: TL-006 | B7: SYN-1001 | C7: Pacific Crest University (fictional) | D7: Quarter | E7: Summer 2025 | F7: ECON 200 | G7: Introduction to Microeconomics | H7: 4 | I7: B+ | J7: No | K7: 46211
A8: TL-007 | B8: SYN-1002 | C8: Northeastern University | D8: Semester | E8: Fall 2024 | F8: CS 2000 | G8: Introduction to Program Design and Implementation | H8: 5 | I8: A | J8: No | K8: 46203
A9: TL-008 | B9: SYN-1002 | C9: Northeastern University | D9: Semester | E9: Fall 2024 | F9: CS 1800 | G9: Discrete Structures | H9: 4 | I9: A- | J9: No | K9: 46203
A10: TL-009 | B10: SYN-1002 | C10: Northeastern University | D10: Semester | E10: Fall 2024 | F10: MATH 1341 | G10: Calculus 1 for Science and Engineering | H10: 4 | I10: B | J10: No | K10: 46203
A11: TL-010 | B11: SYN-1002 | C11: Northeastern University | D11: Semester | E11: Fall 2024 | F11: ENGW 1111 | G11: First-Year Writing | H11: 4 | I11: A | J11: No | K11: 46203
A12: TL-011 | B12: SYN-1002 | C12: Northeastern University | D12: Semester | E12: Spring 2025 | F12: CS 2100 | G12: Program Design and Implementation 1 | H12: 5 | I12: B+ | J12: No | K12: 46203
A13: TL-012 | B13: SYN-1002 | C13: Northeastern University | D13: Semester | E13: Spring 2025 | F13: MATH 1342 | G13: Calculus 2 for Science and Engineering | H13: 4 | I13: C- | J13: No | K13: 46203
... A36: TL-035 | B36: SYN-1005 | C36: New York University | D36: Semester | E36: Summer 2026 | F36: ECON-UA 266 | G36: Intro to Econometrics | H36: 4 | I36: B+ | J36: Yes | K36: 46259

Sheet Syllabi
A1: File | B1: Institution | C1: Course code | D1: Course title | E1: Needed for student
A2: syllabi/HCC_CSC215_Data_Structures_in_Java.pdf | B2: Harborview Community College (fictional) | C2: CSC 215 | D2: Data Structures in Java | E2: SYN-1001
A3: syllabi/HCC_MAT210_Discrete_Mathematics.pdf | B3: Harborview Community College (fictional) | C3: MAT 210 | D3: Discrete Mathematics | E3: SYN-1001
A4: syllabi/NU_CS2100_Program_Design_1.pdf | B4: Northeastern University | C4: CS 2100 | D4: Program Design and Implementation 1 | E4: SYN-1002
A5: syllabi/PCU_CHEM237_Organic_Chemistry_I.pdf | B5: Pacific Crest University (fictional) | C5: CHEM 237 | D5: Organic Chemistry I | E5: SYN-1004

Sheet Answer Key
A1: Line ID | B1: Student ID | C1: Course code | D1: Expected path | E1: Expected BU course | F1: Expected units | G1: Secure units | H1: Pending units | I1: Flags the agent must raise | J1: Why
A2: TL-001 | B2: SYN-1001 | C2: CSC 110 | D2: Existing equivalency | E2: CAS CS 111 | F2: 4 | G2: 4 | H2: 0 | I2: No BU Hub units (all transfer courses) | J2: D-012: Syllabus confirms Python, recursion, dictionaries and intro to classes. Meets CS 111.
A3: TL-002 | B3: SYN-1001 | C3: MAT 151 | D3: Existing equivalency | E3: CAS MA 123 | F3: 4 | G3: 4 | H3: 0 | I3: No BU Hub units (all transfer courses) | J3: D-108: Limits, derivatives, applications and intro to integration. Meets MA 123.
A4: TL-003 | B4: SYN-1001 | C4: ENG 101 | D4: Existing equivalency | E4: CAS general elective | F4: 3 | G4: 3 | H4: 0 | I4: No BU Hub units (all transfer courses) | J4: D-039: Composition course. General elective credit; transfer courses do not earn BU Hub units.
A5: TL-004 | B5: SYN-1001 | C5: CSC 215 | D5: Maybe → syllabus review | E5: CAS CS 112 | F5: Pending (4 if approved) | G5: 0 | H5: 4 | I5: No BU Hub units (all transfer courses) | J5: Likely equivalent: syllabus covers linked lists, stacks, queues, BSTs, heaps, hash tables and Big-O in Java.
A6: TL-005 | B6: SYN-1001 | C6: MAT 210 | D6: Maybe → syllabus review | E6: CAS CS 131 (conditional) or CAS MA 293 | F6: Pending (3 if approved) | G6: 0 | H6: 3 | I6: No BU Hub units (all transfer courses) | J6: Partial: logic, proofs, induction, counting and graphs covered; recurrences and discrete probability missing; 3 vs 4 credits. Department decides.
A7: TL-006 | B7: SYN-1001 | C7: ECON 200 | D7: Existing equivalency | E7: CAS EC 101 | F7: 2.66 | G7: 2.66 | H7: 0 | I7: Quarter conversion 4 × 2/3 = 2.66; No BU Hub units (all transfer courses) | J7: D-086: Principles of microeconomics. Meets EC 101; units reduced by quarter conversion.
A8: TL-007 | B8: SYN-1002 | C8: CS 2000 | D8: Existing equivalency | E8: CAS CS 111 | F8: 5 | G8: 5 | H8: 0 | I8: No BU Hub units (all transfer courses) | J8: D-005: Content and level align with CAS CS 111 (Introduction to Computer Science 1).
A9: TL-008 | B9: SYN-1002 | C9: CS 1800 | D9: Existing equivalency | E9: CAS CS 131 | F9: 4 | G9: 4 | H9: 0 | I9: No BU Hub units (all transfer courses) | J9: D-027: Content and level align with CAS CS 131 (Combinatoric Structures).
A10: TL-009 | B10: SYN-1002 | C10: MATH 1341 | D10: Existing equivalency | E10: CAS MA 123 | F10: 4 | G10: 4 | H10: 0 | I10: No BU Hub units (all transfer courses) | J10: D-010: Content and level align with CAS MA 123 (Calculus I).
A11: TL-010 | B11: SYN-1002 | C11: ENGW 1111 | D11: Maybe → request syllabus | E11: CAS general elective (likely) | F11: Pending (4 if approved) | G11: 0 | H11: 4 | I11: No BU Hub units (all transfer courses) | J11: Course not in catalogue data; request syllabus. Writing courses typically earn elective credit, no Hub units.
A12: TL-011 | B12: SYN-1002 | C12: CS 2100 | D12: Maybe → syllabus review | E12: CAS CS 112 (with CS 2700) | F12: Pending (5 if approved) | G12: 0 | H12: 5 | I12: No BU Hub units (all transfer courses) | J12: Program design without asymptotic analysis. With CS 2700 (also on transcript) the pair likely covers CS 112; flag combined review.
A13: TL-012 | B13: SYN-1002 | C13: MATH 1342 | D13: Existing equivalency | E13: CAS MA 124 | F13: 0 | G13: 0 | H13: 0 | I13: Grade below C: no credit; No BU Hub units (all transfer courses) | J13: D-070: Content and level align with CAS MA 124 (Calculus II).
A14: TL-013 | B14: SYN-1002 | C14: MATH 2331 | D14: Existing equivalency | E14: CAS MA 242 | F14: 4 | G14: 4 | H14: 0 | I14: No BU Hub units (all transfer courses) | J14: D-069: Full linear-algebra content. Per BU CS BA rules MA 242 may also substitute for CS 132.
A15: TL-014 | B15: SYN-1002 | C15: CS 2700 | D15: Existing equivalency | E15: CAS CS elective | F15: 5 | G15: 5 | H15: 0 | I15: No BU Hub units (all transfer courses) | J15: D-020: Data-structures content matches part of CS 112 but assumes CS 2100 design content. If student also completed CS 2100, refer to evaluator for combined CS 112 review.
A16: TL-015 | B16: SYN-1002 | C16: CS 3000 | D16: Existing equivalency | E16: CAS CS 330 | F16: 4 | G16: 4 | H16: 0 | I16: No BU Hub units (all transfer courses) | J16: D-007: Content and level align with CAS CS 330 (Introduction to the Analysis of Algorithms).
A17: TL-016 | B17: SYN-1002 | C17: CS 3800 | D17: Existing equivalency | E17: CAS CS elective | F17: 4 | G17: 4 | H17: 0 | I17: Group C requirement must be taken at BU: elective credit only; No BU Hub units (all transfer courses) | J17: D-006: Comparable to CAS CS 332, but CS Group C courses must be taken at BU. Elective credit only.
A18: TL-017 | B18: SYN-1003 | C18: PSYCH-UA 1 | D18: Existing equivalency | E18: CAS PS 101 | F18: 4 | G18: 4 | H18: 0 | I18: No BU Hub units (all transfer courses) | J18: D-094: Content and level align with CAS PS 101 (General Psychology).
A19: TL-018 | B19: SYN-1003 | C19: MATH-UA 121 | D19: Existing equivalency | E19: CAS MA 123 | F19: 4 | G19: 4 | H19: 0 | I19: No BU Hub units (all transfer courses) | J19: D-085: Content and level align with CAS MA 123 (Calculus I).
A20: TL-019 | B20: SYN-1003 | C20: EXPOS-UA 1 | D20: Maybe → request syllabus | E20: CAS general elective (likely) | F20: Pending (4 if approved) | G20: 0 | H20: 4 | I20: No BU Hub units (all transfer courses) | J20: Course not in catalogue data; request syllabus.
A21: TL-020 | B21: SYN-1003 | C21: PSYCH-UA 10 | D21: Existing equivalency | E21: CAS PS elective | F21: 4 | G21: 4 | H21: 0 | I21: No BU Hub units (all transfer courses) | J21: D-099: Statistics only; does not cover experimental design required for PS 211.
A22: TL-021 | B22: SYN-1003 | C22: BIOL-UA 11 | D22: Existing equivalency | E22: CAS BI 107 | F22: 4 | G22: 4 | H22: 0 | I22: No BU Hub units (all transfer courses) | J22: D-011: Content and level align with CAS BI 107 (Biology 1).
A23: TL-022 | B23: SYN-1003 | C23: PSYCH-UA 25 | D23: Maybe → syllabus review | E23: CAS PS 231 (uncertain) | F23: Pending (4 if approved) | G23: 0 | H23: 4 | I23: No BU Hub units (all transfer courses) | J23: Cognitive neuroscience; limited neurotransmission/hormone coverage vs PS 231. Likely elective unless syllabus shows physiological depth.
A24: TL-023 | B24: SYN-1003 | C24: PSYCH-UA 32 | D24: Existing equivalency | E24: CAS PS 261 | F24: 4 | G24: 4 | H24: 0 | I24: No BU Hub units (all transfer courses) | J24: D-001: Content and level align with CAS PS 261 (Social Psychology).
A25: TL-024 | B25: SYN-1003 | C25: PSYCH-UA 34 | D25: Existing equivalency | E25: CAS PS 241 | F25: Hold (4 if grade accepted) | G25: 0 | H25: 4 | I25: Pass/Fail grade: cannot confirm C or higher, needs evaluator decision; No BU Hub units (all transfer courses) | J25: D-110: Content and level align with CAS PS 241 (Developmental Psychology).
A26: TL-025 | B26: SYN-1004 | C26: MAT 090 | D26: Existing equivalency | E26: — | F26: 0 | G26: 0 | H26: 0 | I26: Pass/Fail grade: cannot confirm C or higher, needs evaluator decision; No BU Hub units (all transfer courses) | J26: D-071: Developmental (pre-college) course; carries no degree credit at the sending institution.
A27: TL-026 | B27: SYN-1004 | C27: BIO 121 | D27: Existing equivalency | E27: CAS BI 107 | F27: 4 | G27: 4 | H27: 0 | I27: No BU Hub units (all transfer courses) | J27: D-026: Intro biology I with lab. Meets BI 107.
A28: TL-027 | B28: SYN-1004 | C28: CHM 121 | D28: Existing equivalency | E28: CAS CH 101 | F28: 4 | G28: 4 | H28: 0 | I28: No BU Hub units (all transfer courses) | J28: D-073: General chemistry I with lab. Meets CH 101.
A29: TL-028 | B29: SYN-1004 | C29: BIO 122 | D29: Existing equivalency | E29: CAS BI 108 | F29: 4 | G29: 4 | H29: 0 | I29: No BU Hub units (all transfer courses) | J29: D-087: Intro biology II with lab. Meets BI 108.
A30: TL-029 | B30: SYN-1004 | C30: CHM 122 | D30: Existing equivalency | E30: CAS CH 102 | F30: 4 | G30: 4 | H30: 0 | I30: No BU Hub units (all transfer courses) | J30: D-055: General chemistry II with lab. Meets CH 102.
A31: TL-030 | B31: SYN-1004 | C31: STA 150 | D31: Existing equivalency | E31: CAS MA elective | F31: 3 | G31: 3 | H31: 0 | I31: No BU Hub units (all transfer courses) | J31: D-105: Non-calculus statistics; elective credit.
A32: TL-031 | B32: SYN-1004 | C32: MATH 124 | D32: Existing equivalency | E32: CAS MA 123 | F32: 0 (deadline; exception needed) | G32: 0 | H32: 0 | I32: Quarter conversion 5 × 2/3 = 3.33; Transcript received > 1 year after BU start: deadline exceeded; No BU Hub units (all transfer courses) | J32: D-025: Quarter calculus I. Accepted for MA 123; 3.33 units after quarter conversion.
A33: TL-032 | B33: SYN-1004 | C33: CHEM 237 | D33: Maybe → syllabus review | E33: CAS CH 203 (partial) / CAS CH elective | F33: 0 (deadline; exception needed) | G33: 0 | H33: 0 | I33: Quarter conversion 4 × 2/3 = 2.66; Transcript received > 1 year after BU start: deadline exceeded; No BU Hub units (all transfer courses) | J33: One quarter covers only part of Orgo I (no eliminations/alkenes, no lab). Likely elective unless paired with next quarter.
A34: TL-033 | B34: SYN-1005 | C34: ECON-UA 12 | D34: Existing equivalency | E34: CAS EC 202 | F34: 4 | G34: 4 | H34: 0 | I34: No BU Hub units (all transfer courses) | J34: D-030: Content and level align with CAS EC 202 (Intermediate Macroeconomic Analysis).
A35: TL-034 | B35: SYN-1005 | C35: ECON-UA 18 | D35: Existing equivalency | E35: CAS EC 203 | F35: 4 | G35: 4 | H35: 0 | I35: No BU Hub units (all transfer courses) | J35: D-063: Content and level align with CAS EC 203 (Empirical Economics 1).
A36: TL-035 | B36: SYN-1005 | C36: ECON-UA 266 | D36: Existing equivalency | E36: CAS EC 204 | F36: Hold (4 if cap allows) | G36: 0 | H36: 4 | I36: Econ cap: this is 200+ level transfer #5 after matriculation (max 4); evaluator must choose which count; No BU Hub units (all transfer courses) | J36: D-075: Syllabus review: covers multiple regression, IV and panel data with an empirical project. Meets EC 204.

Sheet Summary
A1: Summary checks (formulas)
A3: Active decisions by outcome | B3: Count
A4: BU equivalent | B4: =COUNTIFS('Past Decisions'!$H:$H,A4,'Past Decisions'!$P:$P,"Active") -> 73
A5: Combined equivalent | B5: =COUNTIFS('Past Decisions'!$H:$H,A5,'Past Decisions'!$P:$P,"Active") -> 2
A6: Elective credit | B6: =COUNTIFS('Past Decisions'!$H:$H,A6,'Past Decisions'!$P:$P,"Active") -> 30
A7: No credit | B7: =COUNTIFS('Past Decisions'!$H:$H,A7,'Past Decisions'!$P:$P,"Active") -> 3
A8: Superseded | B8: =COUNTIF('Past Decisions'!$P:$P,"Superseded") -> 3
A9: Total decisions | B9: =SUM(B4:B8) -> 111
A11: Student | B11: Transcript lines | C11: Existing equivalency | D11: Maybe (syllabus) | E11: Secure units | F11: Pending units
A12: SYN-1001 | B12: =COUNTIF('Transcript Lines'!$B:$B,A12) -> 6 | C12: =COUNTIFS('Answer Key'!$B:$B,A12,'Answer Key'!$D:$D,"Existing equivalency") -> 4 | D12: =COUNTIFS('Answer Key'!$B:$B,A12,'Answer Key'!$D:$D,"Maybe*") -> 2 | E12: =SUMIF('Answer Key'!$B:$B,A12,'Answer Key'!$G:$G) -> 13.66 | F12: =SUMIF('Answer Key'!$B:$B,A12,'Answer Key'!$H:$H) -> 7
A13: SYN-1002 | B13: =COUNTIF('Transcript Lines'!$B:$B,A13) -> 10 | C13: =COUNTIFS('Answer Key'!$B:$B,A13,'Answer Key'!$D:$D,"Existing equivalency") -> 8 | D13: =COUNTIFS('Answer Key'!$B:$B,A13,'Answer Key'!$D:$D,"Maybe*") -> 2 | E13: =SUMIF('Answer Key'!$B:$B,A13,'Answer Key'!$G:$G) -> 30 | F13: =SUMIF('Answer Key'!$B:$B,A13,'Answer Key'!$H:$H) -> 9
A14: SYN-1003 | B14: =COUNTIF('Transcript Lines'!$B:$B,A14) -> 8 | C14: =COUNTIFS('Answer Key'!$B:$B,A14,'Answer Key'!$D:$D,"Existing equivalency") -> 6 | D14: =COUNTIFS('Answer Key'!$B:$B,A14,'Answer Key'!$D:$D,"Maybe*") -> 2 | E14: =SUMIF('Answer Key'!$B:$B,A14,'Answer Key'!$G:$G) -> 20 | F14: =SUMIF('Answer Key'!$B:$B,A14,'Answer Key'!$H:$H) -> 12
A15: SYN-1004 | B15: =COUNTIF('Transcript Lines'!$B:$B,A15) -> 8 | C15: =COUNTIFS('Answer Key'!$B:$B,A15,'Answer Key'!$D:$D,"Existing equivalency") -> 7 | D15: =COUNTIFS('Answer Key'!$B:$B,A15,'Answer Key'!$D:$D,"Maybe*") -> 1 | E15: =SUMIF('Answer Key'!$B:$B,A15,'Answer Key'!$G:$G) -> 19 | F15: =SUMIF('Answer Key'!$B:$B,A15,'Answer Key'!$H:$H) -> 0
A16: SYN-1005 | B16: =COUNTIF('Transcript Lines'!$B:$B,A16) -> 3 | C16: =COUNTIFS('Answer Key'!$B:$B,A16,'Answer Key'!$D:$D,"Existing equivalency") -> 3 | D16: =COUNTIFS('Answer Key'!$B:$B,A16,'Answer Key'!$D:$D,"Maybe*") -> 0 | E16: =SUMIF('Answer Key'!$B:$B,A16,'Answer Key'!$G:$G) -> 8 | F16: =SUMIF('Answer Key'!$B:$B,A16,'Answer Key'!$H:$H) -> 4
A18: Demo check (SYN-1001): needs 3 existing, 2 maybe, 1 quarter course | B18: =IF(AND(C12-COUNTIFS('Transcript Lines'!$B:$B,"SYN-1001",'Transcript Lines'!$D:$D,"Quarter")=3,D12=2,COUNTIFS('Transcript Lines'!$B:$B,"SYN-1001",'Transcript Lines'!$D:$D,"Quarter")=1),"OK","CHECK") -> OK
